{
  "symbol": "BTCUSDT",
  "timeframe": "1h",
  "start_date": "2020-05-03",
  "end_date": "2026-01-16",
  "initial_capital": 10000,
  "final_capital": 121191.15917540703,
  "total_trades": 49963,
  "winning_trades": 32557,
  "losing_trades": 17406,
  "total_return_pct": 1111.9115917540703,
  "cagr": 0.0,
  "max_drawdown_pct": 0.47981275356571496,
  "max_drawdown_duration": 0,
  "profit_factor": 2.394351656736004,
  "expectancy_r": 0.009988438820939437,
  "win_rate": 65.16222004283169,
  "avg_win": 5.86464186828105,
  "avg_loss": 4.5814079128013425,
  "sharpe_ratio": 5.56356529320129,
  "sortino_ratio": 11.647407135034287,
  "calmar_ratio": 0.0,
  "max_win_streak": 37,
  "max_loss_streak": 28,
  "total_commission": 40176.50244318616,
  "total_slippage": 24090.14398174815,
  "trades": [
    {
      "id": 1,
      "entry_time": "2020-05-03 19:00:00",
      "entry_price": 8869.715607601693,
      "side": "SELL",
      "quantity": 0.01127431863929167,
      "stop_loss": 8985.931525097563,
      "take_profit": 8660.526956109126,
      "exit_time": "2020-05-04 01:00:00",
      "exit_price": 8663.157232240017,
      "exit_reason": "TP",
      "commission": 0.14825339629391854,
      "slippage": 0.05924280734204574,
      "pnl_gross": 2.328804941441945,
      "pnl_net": 2.1805515451480266,
      "pnl_r": 0.043611030902960535,
      "holding_bars": 6
    },
    {
      "id": 2,
      "entry_time": "2020-05-03 20:00:00",
      "entry_price": 8839.660222848914,
      "side": "SELL",
      "quantity": 0.011315118793470514,
      "stop_loss": 8953.507951314174,
      "take_profit": 8634.734311611446,
      "exit_time": "2020-05-03 22:00:00",
      "exit_price": 8956.08592622664,
      "exit_reason": "SL",
      "commission": 0.15102073627142648,
      "slippage": 0.0731833829258129,
      "pnl_gross": -1.3173706643323386,
      "pnl_net": -1.468391400603765,
      "pnl_r": -0.029361425601878904,
      "holding_bars": 2
    },
    {
      "id": 3,
      "entry_time": "2020-05-03 21:00:00",
      "entry_price": 8849.100594893798,
      "side": "SELL",
      "quantity": 0.00704731373970198,
      "stop_loss": 8961.792495548301,
      "take_profit": 8646.255173715692,
      "exit_time": "2020-05-04 01:00:00",
      "exit_price": 8649.598051274628,
      "exit_reason": "TP",
      "commission": 0.09248911454703539,
      "slippage": 0.07218057935194412,
      "pnl_gross": 1.4059570167528699,
      "pnl_net": 1.3134679022058344,
      "pnl_r": 0.02626748737835587,
      "holding_bars": 4
    },
    {
      "id": 4,
      "entry_time": "2020-05-03 22:00:00",
      "entry_price": 8892.36172587142,
      "side": "SELL",
      "quantity": 0.01124788434881914,
      "stop_loss": 9003.688285415194,
      "take_profit": 8691.973918692627,
      "exit_time": "2020-05-04 01:00:00",
      "exit_price": 8699.096943610451,
      "exit_reason": "TP",
      "commission": 0.14840001948102294,
      "slippage": 0.11766748181237441,
      "pnl_gross": 2.17381991957109,
      "pnl_net": 2.025419900090067,
      "pnl_r": 0.0405001941688806,
      "holding_bars": 3
    },
    {
      "id": 5,
      "entry_time": "2020-05-03 23:00:00",
      "entry_price": 8889.70009885991,
      "side": "SELL",
      "quantity": 0.011253530419130612,
      "stop_loss": 8997.03839290451,
      "take_profit": 8696.491169579633,
      "exit_time": "2020-05-04 01:00:00",
      "exit_price": 8700.49398810029,
      "exit_reason": "TP",
      "commission": 0.14846383817701353,
      "slippage": 0.09523547313079408,
      "pnl_gross": 2.12923672291878,
      "pnl_net": 1.9807728847417665,
      "pnl_r": 0.0395994157816355,
      "holding_bars": 2
    },
    {
      "id": 6,
      "entry_time": "2020-05-04 00:00:00",
      "entry_price": 8803.880018163116,
      "side": "SELL",
      "quantity": 0.007160559749699666,
      "stop_loss": 8916.774802650547,
      "take_profit": 8600.66940608574,
      "exit_time": "2020-05-04 05:00:00",
      "exit_price": 8603.763341400936,
      "exit_reason": "TP",
      "commission": 0.09348635278321576,
      "slippage": 0.038623466052384814,
      "pnl_gross": 1.4329474208669235,
      "pnl_net": 1.3394610680837078,
      "pnl_r": 0.02677307232413714,
      "holding_bars": 5
    },
    {
      "id": 7,
      "entry_time": "2020-05-04 01:00:00",
      "entry_price": 8690.946101501433,
      "side": "SELL",
      "quantity": 0.01151470871528108,
      "stop_loss": 8812.433831605613,
      "take_profit": 8472.26818731391,
      "exit_time": "2020-05-04 13:00:00",
      "exit_price": 8816.60325902646,
      "exit_reason": "SL",
      "commission": 0.15119574840366318,
      "slippage": 0.07983522839014631,
      "pnl_gross": -1.4469055668908792,
      "pnl_net": -1.5981013152945425,
      "pnl_r": -0.031938483549321856,
      "holding_bars": 12
    },
    {
      "id": 8,
      "entry_time": "2020-05-04 02:00:00",
      "entry_price": 8743.837279378959,
      "side": "SELL",
      "quantity": 0.011443228940435,
      "stop_loss": 8864.080543686616,
      "take_profit": 8527.399403625175,
      "exit_time": "2020-05-04 05:00:00",
      "exit_price": 8530.745472385446,
      "exit_reason": "TP",
      "commission": 0.14825775395919727,
      "slippage": 0.07104859833329841,
      "pnl_gross": 2.43845833275775,
      "pnl_net": 2.2902005787985527,
      "pnl_r": 0.04577758335043123,
      "holding_bars": 3
    },
    {
      "id": 9,
      "entry_time": "2020-05-04 03:00:00",
      "entry_price": 8727.90055625631,
      "side": "SELL",
      "quantity": 0.011466747720892876,
      "stop_loss": 8843.481074764268,
      "take_profit": 8519.85562294199,
      "exit_time": "2020-05-04 14:00:00",
      "exit_price": 8846.173683621619,
      "exit_reason": "SL",
      "commission": 0.15113810680269185,
      "slippage": 0.06458132632692809,
      "pnl_gross": -1.3562081136590187,
      "pnl_net": -1.5073462204617105,
      "pnl_r": -0.030122635380163267,
      "holding_bars": 11
    },
    {
      "id": 10,
      "entry_time": "2020-05-04 04:00:00",
      "entry_price": 8683.059615758957,
      "side": "SELL",
      "quantity": 0.005794979672651224,
      "stop_loss": 8799.112418375558,
      "take_profit": 8474.164571049076,
      "exit_time": "2020-05-04 13:00:00",
      "exit_price": 8805.308357857535,
      "exit_reason": "SL",
      "commission": 0.0760085526862142,
      "slippage": 0.0637814222455326,
      "pnl_gross": -0.708428975468442,
      "pnl_net": -0.7844375281546562,
      "pnl_r": -0.015678471702260294,
      "holding_bars": 9
    },
    {
      "id": 11,
      "entry_time": "2020-05-04 05:00:00",
      "entry_price": 8609.457830835509,
      "side": "BUY",
      "quantity": 0.011621837047134407,
      "stop_loss": 8488.429220215095,
      "take_profit": 8827.30932995225,
      "exit_time": "2020-05-04 13:00:00",
      "exit_price": 8824.947339762004,
      "exit_reason": "TP",
      "commission": 0.15196486192980135,
      "slippage": 0.06635860952959446,
      "pnl_gross": 2.5043839581107465,
      "pnl_net": 2.3524190961809452,
      "pnl_r": 0.04702124315507661,
      "holding_bars": 8
    },
    {
      "id": 12,
      "entry_time": "2020-05-04 06:00:00",
      "entry_price": 8628.140832887448,
      "side": "BUY",
      "quantity": 0.011599398074685192,
      "stop_loss": 8511.61881706212,
      "take_profit": 8837.880461373035,
      "exit_time": "2020-05-04 14:00:00",
      "exit_price": 8835.432676636461,
      "exit_reason": "TP",
      "commission": 0.15192520570762125,
      "slippage": 0.11354207242190924,
      "pnl_gross": 2.40446061328025,
      "pnl_net": 2.252535407572629,
      "pnl_r": 0.04501413859093965,
      "holding_bars": 8
    },
    {
      "id": 13,
      "entry_time": "2020-05-04 07:00:00",
      "entry_price": 8651.91343839865,
      "side": "BUY",
      "quantity": 0.011570130264469096,
      "stop_loss": 8536.841250911222,
      "take_profit": 8859.043375876017,
      "exit_time": "2020-05-04 14:00:00",
      "exit_price": 8855.288960385475,
      "exit_reason": "TP",
      "commission": 0.1519204592402686,
      "slippage": 0.08397431493843428,
      "pnl_gross": 2.353081281991968,
      "pnl_net": 2.2011608227516994,
      "pnl_r": 0.043977582887826265,
      "holding_bars": 7
    },
    {
      "id": 14,
      "entry_time": "2020-05-04 08:00:00",
      "entry_price": 8693.952916834927,
      "side": "BUY",
      "quantity": 0.011516714903473602,
      "stop_loss": 8581.93285352083,
      "take_profit": 8895.589030800304,
      "exit_time": "2020-05-04 20:00:00",
      "exit_price": 8892.191249887997,
      "exit_reason": "TP",
      "commission": 0.15190095646464996,
      "slippage": 0.06979932807100694,
      "pnl_gross": 2.283054364712057,
      "pnl_net": 2.131153408247407,
      "pnl_r": 0.04256952543869902,
      "holding_bars": 12
    },
    {
      "id": 15,
      "entry_time": "2020-05-04 09:00:00",
      "entry_price": 8633.022671266574,
      "side": "BUY",
      "quantity": 0.011600466311158224,
      "stop_loss": 8521.770445782613,
      "take_profit": 8833.276677137703,
      "exit_time": "2020-05-04 13:00:00",
      "exit_price": 8830.173122270851,
      "exit_reason": "TP",
      "commission": 0.1519359108660682,
      "slippage": 0.0648028280673042,
      "pnl_gross": 2.2870371651047745,
      "pnl_net": 2.1351012542387062,
      "pnl_r": 0.042639307498105246,
      "holding_bars": 4
    },
    {
      "id": 16,
      "entry_time": "2020-05-04 10:00:00",
      "entry_price": 8628.174120328074,
      "side": "BUY",
      "quantity": 0.01160945969298852,
      "stop_loss": 8519.610506707746,
      "take_profit": 8823.588624844666,
      "exit_time": "2020-05-04 13:00:00",
      "exit_price": 8818.201165439239,
      "exit_reason": "TP",
      "commission": 0.15190724300165004,
      "slippage": 0.11727388275161169,
      "pnl_gross": 2.206111320795777,
      "pnl_net": 2.054204077794127,
      "pnl_r": 0.04101499603026351,
      "holding_bars": 3
    },
    {
      "id": 17,
      "entry_time": "2020-05-04 11:00:00",
      "entry_price": 8675.196946735898,
      "side": "BUY",
      "quantity": 0.011548899965033091,
      "stop_loss": 8568.940503446169,
      "take_profit": 8866.45854465741,
      "exit_time": "2020-05-04 16:00:00",
      "exit_price": 8863.305633300248,
      "exit_reason": "TP",
      "commission": 0.15191280887498418,
      "slippage": 0.06917627192147277,
      "pnl_gross": 2.172448403685444,
      "pnl_net": 2.0205355948104597,
      "pnl_r": 0.04033448709084373,
      "holding_bars": 5
    },
    {
      "id": 18,
      "entry_time": "2020-05-04 12:00:00",
      "entry_price": 8717.34003555301,
      "side": "BUY",
      "quantity": 0.011495385824353065,
      "stop_loss": 8611.462896396373,
      "take_profit": 8907.918886034957,
      "exit_time": "2020-05-04 20:00:00",
      "exit_price": 8900.348960319,
      "exit_reason": "TP",
      "commission": 0.15189159925575607,
      "slippage": 0.11874689033742607,
      "pnl_gross": 2.103758199485046,
      "pnl_net": 1.9518666002292897,
      "pnl_r": 0.03895584142102665,
      "holding_bars": 8
    },
    {
      "id": 19,
      "entry_time": "2020-05-04 13:00:00",
      "entry_price": 8834.200690340156,
      "side": "BUY",
      "quantity": 0.011345531899265076,
      "stop_loss": 8727.019475274812,
      "take_profit": 9027.126877457775,
      "exit_time": "2020-05-05 04:00:00",
      "exit_price": 9023.215236642327,
      "exit_reason": "TP",
      "commission": 0.15195141152851802,
      "slippage": 0.09793838849093266,
      "pnl_gross": 2.144470564496395,
      "pnl_net": 1.992519152967877,
      "pnl_r": 0.03975945091421095,
      "holding_bars": 15
    },
    {
      "id": 20,
      "entry_time": "2020-05-04 14:00:00",
      "entry_price": 8784.322474222055,
      "side": "BUY",
      "quantity": 0.011412221172717313,
      "stop_loss": 8678.958893621822,
      "take_profit": 8973.976919302475,
      "exit_time": "2020-05-05 04:00:00",
      "exit_price": 8969.598408412667,
      "exit_reason": "TP",
      "commission": 0.15195875384666402,
      "slippage": 0.09815634439983045,
      "pnl_gross": 2.114409938965073,
      "pnl_net": 1.962451185118409,
      "pnl_r": 0.0391516805156596,
      "holding_bars": 14
    },
    {
      "id": 21,
      "entry_time": "2020-05-04 15:00:00",
      "entry_price": 8840.084152729412,
      "side": "SELL",
      "quantity": 0.011342454857648208,
      "stop_loss": 8942.689787003565,
      "take_profit": 8655.394011035938,
      "exit_time": "2020-05-04 22:00:00",
      "exit_price": 8947.944947977277,
      "exit_reason": "SL",
      "commission": 0.15131993781097372,
      "slippage": 0.14939156644069487,
      "pnl_gross": -1.2234062010089461,
      "pnl_net": -1.37472613881992,
      "pnl_r": -0.027420964547260236,
      "holding_bars": 7
    },
    {
      "id": 22,
      "entry_time": "2020-05-04 16:00:00",
      "entry_price": 8832.218942884752,
      "side": "BUY",
      "quantity": 0.011350998976256316,
      "stop_loss": 8729.968854982266,
      "take_profit": 9016.269101109228,
      "exit_time": "2020-05-05 04:00:00",
      "exit_price": 9011.542579453067,
      "exit_reason": "TP",
      "commission": 0.15190838907946386,
      "slippage": 0.09064299982883886,
      "pnl_gross": 2.035502415105505,
      "pnl_net": 1.8835940260260409,
      "pnl_r": 0.037576245901432034,
      "holding_bars": 12
    },
    {
      "id": 23,
      "entry_time": "2020-05-04 17:00:00",
      "entry_price": 8802.993393001892,
      "side": "BUY",
      "quantity": 0.011390823512230617,
      "stop_loss": 8700.566774680497,
      "take_profit": 8987.361305980405,
      "exit_time": "2020-05-05 04:00:00",
      "exit_price": 8984.05688467712,
      "exit_reason": "TP",
      "commission": 0.15195686288716065,
      "slippage": 0.07697707007870869,
      "pnl_gross": 2.062462278180758,
      "pnl_net": 1.9105054152935974,
      "pnl_r": 0.038105947938187335,
      "holding_bars": 11
    },
    {
      "id": 24,
      "entry_time": "2020-05-04 18:00:00",
      "entry_price": 8848.935698086494,
      "side": "BUY",
      "quantity": 0.011333843141707656,
      "stop_loss": 8747.992274916262,
      "take_profit": 9030.633859792913,
      "exit_time": "2020-05-05 04:00:00",
      "exit_price": 9026.219534081067,
      "exit_reason": "TP",
      "commission": 0.15194565415129652,
      "slippage": 0.09010432270323152,
      "pnl_gross": 2.0093071887227123,
      "pnl_net": 1.8573615345714158,
      "pnl_r": 0.03703891070332539,
      "holding_bars": 10
    },
    {
      "id": 25,
      "entry_time": "2020-05-04 19:00:00",
      "entry_price": 8833.191829781794,
      "side": "BUY",
      "quantity": 0.011356146761163838,
      "stop_loss": 8734.158673250718,
      "take_profit": 9011.451511537729,
      "exit_time": "2020-05-05 04:00:00",
      "exit_price": 9009.001644675262,
      "exit_reason": "TP",
      "commission": 0.15196392572776055,
      "slippage": 0.062478074527637,
      "pnl_gross": 1.9965220599832678,
      "pnl_net": 1.8445581342555073,
      "pnl_r": 0.03677677852302171,
      "holding_bars": 9
    },
    {
      "id": 26,
      "entry_time": "2020-05-04 20:00:00",
      "entry_price": 8908.09485931624,
      "side": "BUY",
      "quantity": 0.011262730129656359,
      "stop_loss": 8809.145135581171,
      "take_profit": 9086.204362039362,
      "exit_time": "2020-05-05 05:00:00",
      "exit_price": 9083.343048418566,
      "exit_reason": "TP",
      "commission": 0.15197453234946479,
      "slippage": 0.09355018420007916,
      "pnl_gross": 1.9737730595704952,
      "pnl_net": 1.8217985272210304,
      "pnl_r": 0.03631631975772245,
      "holding_bars": 9
    },
    {
      "id": 27,
      "entry_time": "2020-05-04 21:00:00",
      "entry_price": 8931.991507974008,
      "side": "SELL",
      "quantity": 0.0059356369334187704,
      "stop_loss": 9028.511607826598,
      "take_profit": 8758.255328239346,
      "exit_time": "2020-05-05 04:00:00",
      "exit_price": 9034.257072761866,
      "exit_reason": "SL",
      "commission": 0.0799808464730988,
      "slippage": 0.06211024940895013,
      "pnl_gross": -0.6070112633717415,
      "pnl_net": -0.6869921098448403,
      "pnl_r": -0.013692236160056095,
      "holding_bars": 7
    },
    {
      "id": 28,
      "entry_time": "2020-05-04 22:00:00",
      "entry_price": 8876.312796899736,
      "side": "BUY",
      "quantity": 0.0113043353394529,
      "stop_loss": 8779.109245598309,
      "take_profit": 9051.279189242305,
      "exit_time": "2020-05-05 04:00:00",
      "exit_price": 9046.952559951746,
      "exit_reason": "TP",
      "commission": 0.15195795147888608,
      "slippage": 0.1210629449482221,
      "pnl_gross": 1.9289691037847012,
      "pnl_net": 1.7770111523058152,
      "pnl_r": 0.035419507543554773,
      "holding_bars": 6
    },
    {
      "id": 29,
      "entry_time": "2020-05-04 23:00:00",
      "entry_price": 8875.657271617338,
      "side": "BUY",
      "quantity": 0.011106056766002955,
      "stop_loss": 8779.814512982484,
      "take_profit": 9048.174237160074,
      "exit_time": "2020-05-05 04:00:00",
      "exit_price": 9044.699480341164,
      "exit_reason": "TP",
      "commission": 0.14926837451570657,
      "slippage": 0.07965295494036585,
      "pnl_gross": 1.8773923659373288,
      "pnl_net": 1.7281239914216222,
      "pnl_r": 0.034438986257288355,
      "holding_bars": 5
    },
    {
      "id": 30,
      "entry_time": "2020-05-05 00:00:00",
      "entry_price": 8904.588452484237,
      "side": "BUY",
      "quantity": 0.008026690010350324,
      "stop_loss": 8809.354617142639,
      "take_profit": 9076.009356099114,
      "exit_time": "2020-05-05 04:00:00",
      "exit_price": 9072.483961287553,
      "exit_reason": "TP",
      "commission": 0.10822229066922481,
      "slippage": 0.051883298517617166,
      "pnl_gross": 1.3476452032942636,
      "pnl_net": 1.239422912625039,
      "pnl_r": 0.02469563531493504,
      "holding_bars": 4
    },
    {
      "id": 31,
      "entry_time": "2020-05-05 01:00:00",
      "entry_price": 8884.58649061341,
      "side": "BUY",
      "quantity": 0.011299148488301138,
      "stop_loss": 8790.70182570355,
      "take_profit": 9053.578887451158,
      "exit_time": "2020-05-05 04:00:00",
      "exit_price": 9050.123797984661,
      "exit_reason": "TP",
      "commission": 0.15198521598414882,
      "slippage": 0.09560864976852804,
      "pnl_gross": 1.8704306163413091,
      "pnl_net": 1.7184454003571603,
      "pnl_r": 0.034235982691030536,
      "holding_bars": 3
    },
    {
      "id": 32,
      "entry_time": "2020-05-05 02:00:00",
      "entry_price": 8857.031071159696,
      "side": "BUY",
      "quantity": 0.011336241869528882,
      "stop_loss": 8765.313205740453,
      "take_profit": 9022.123228914332,
      "exit_time": "2020-05-05 04:00:00",
      "exit_price": 9016.78429548714,
      "exit_reason": "TP",
      "commission": 0.15196642059570792,
      "slippage": 0.09771845691340955,
      "pnl_gross": 1.8110011904130061,
      "pnl_net": 1.6590347698172982,
      "pnl_r": 0.03304670868300261,
      "holding_bars": 2
    },
    {
      "id": 33,
      "entry_time": "2020-05-05 03:00:00",
      "entry_price": 8854.16659458483,
      "side": "BUY",
      "quantity": 0.009442255816709391,
      "stop_loss": 8764.801391858382,
      "take_profit": 9015.023959492439,
      "exit_time": "2020-05-05 04:00:00",
      "exit_price": 9010.742583405541,
      "exit_reason": "TP",
      "commission": 0.12651378195064844,
      "slippage": 0.07976790021452261,
      "pnl_gross": 1.4784305411993768,
      "pnl_net": 1.3519167592487285,
      "pnl_r": 0.02692470302552822,
      "holding_bars": 1
    },
    {
      "id": 34,
      "entry_time": "2020-05-05 04:00:00",
      "entry_price": 9036.949376043638,
      "side": "SELL",
      "quantity": 0.011113878345953506,
      "stop_loss": 9137.048888202193,
      "take_profit": 8856.770254158238,
      "exit_time": "2020-05-05 10:00:00",
      "exit_price": 8864.055821295527,
      "exit_reason": "TP",
      "commission": 0.1492121955251317,
      "slippage": 0.15710790808998726,
      "pnl_gross": 1.9215179342699529,
      "pnl_net": 1.7723057387448211,
      "pnl_r": 0.03529239662951856,
      "holding_bars": 6
    },
    {
      "id": 35,
      "entry_time": "2020-05-05 05:00:00",
      "entry_price": 9002.521299016173,
      "side": "SELL",
      "quantity": 0.011158349500628762,
      "stop_loss": 9104.714851803981,
      "take_profit": 8818.572903998118,
      "exit_time": "2020-05-05 10:00:00",
      "exit_price": 8821.241342881907,
      "exit_reason": "TP",
      "commission": 0.14916282973091177,
      "slippage": 0.07361319234740951,
      "pnl_gross": 2.022785108004784,
      "pnl_net": 1.8736222782738723,
      "pnl_r": 0.0373033572653012,
      "holding_bars": 5
    },
    {
      "id": 36,
      "entry_time": "2020-05-05 06:00:00",
      "entry_price": 9022.288033336383,
      "side": "SELL",
      "quantity": 0.011135979575560695,
      "stop_loss": 9123.730734014549,
      "take_profit": 8839.691172115683,
      "exit_time": "2020-05-05 10:00:00",
      "exit_price": 8845.00106985517,
      "exit_reason": "TP",
      "commission": 0.14922732489283447,
      "slippage": 0.08910859855938422,
      "pnl_gross": 1.974264004339955,
      "pnl_net": 1.8250366794471207,
      "pnl_r": 0.036329253964909054,
      "holding_bars": 4
    },
    {
      "id": 37,
      "entry_time": "2020-05-05 07:00:00",
      "entry_price": 9009.715120067844,
      "side": "SELL",
      "quantity": 0.01115354528879903,
      "stop_loss": 9108.924861301533,
      "take_profit": 8831.137585847204,
      "exit_time": "2020-05-05 10:00:00",
      "exit_price": 8835.155105195288,
      "exit_reason": "TP",
      "commission": 0.14927517617266028,
      "slippage": 0.08758209099789643,
      "pnl_gross": 1.9469630314944775,
      "pnl_net": 1.7976878553218172,
      "pnl_r": 0.0357783481621102,
      "holding_bars": 3
    },
    {
      "id": 38,
      "entry_time": "2020-05-05 08:00:00",
      "entry_price": 9029.40651071134,
      "side": "SELL",
      "quantity": 0.00833020334891998,
      "stop_loss": 9126.016186361094,
      "take_profit": 8855.509094541781,
      "exit_time": "2020-05-05 10:00:00",
      "exit_price": 8859.223128674354,
      "exit_reason": "TP",
      "commission": 0.11176194189719994,
      "slippage": 0.057291168635825555,
      "pnl_gross": 1.4176621789750339,
      "pnl_net": 1.3059002370778339,
      "pnl_r": 0.025985933182656233,
      "holding_bars": 2
    },
    {
      "id": 39,
      "entry_time": "2020-05-05 09:00:00",
      "entry_price": 8996.672708172271,
      "side": "SELL",
      "quantity": 0.007834559106301426,
      "stop_loss": 9093.157618743977,
      "take_profit": 8822.999869143201,
      "exit_time": "2020-05-05 10:00:00",
      "exit_price": 8827.753942642752,
      "exit_reason": "TP",
      "commission": 0.10473489309880848,
      "slippage": 0.06339227990725355,
      "pnl_gross": 1.323404052704489,
      "pnl_net": 1.2186691596056805,
      "pnl_r": 0.024246983301601778,
      "holding_bars": 1
    },
    {
      "id": 40,
      "entry_time": "2020-05-05 10:00:00",
      "entry_price": 8852.311812441967,
      "side": "BUY",
      "quantity": 0.011356749551238565,
      "stop_loss": 8745.289064534716,
      "take_profit": 9044.952758675021,
      "exit_time": "2020-05-06 03:00:00",
      "exit_price": 9039.937035276005,
      "exit_reason": "TP",
      "commission": 0.15239834180397735,
      "slippage": 0.10309130108842104,
      "pnl_gross": 2.1308126652214985,
      "pnl_net": 1.978414323417521,
      "pnl_r": 0.039358314503427735,
      "holding_bars": 17
    },
    {
      "id": 41,
      "entry_time": "2020-05-05 11:00:00",
      "entry_price": 8847.398711567921,
      "side": "BUY",
      "quantity": 0.007142524524657119,
      "stop_loss": 8743.728159549562,
      "take_profit": 9034.005705200969,
      "exit_time": "2020-05-05 23:00:00",
      "exit_price": 9031.161045618921,
      "exit_reason": "TP",
      "commission": 0.09577353864844114,
      "slippage": 0.039379388652196604,
      "pnl_gross": 1.312526977667501,
      "pnl_net": 1.21675343901906,
      "pnl_r": 0.024201170397018933,
      "holding_bars": 12
    },
    {
      "id": 42,
      "entry_time": "2020-05-05 12:00:00",
      "entry_price": 8874.341583891475,
      "side": "BUY",
      "quantity": 0.0064821155887387185,
      "stop_loss": 8772.52904196564,
      "take_profit": 9057.60415935798,
      "exit_time": "2020-05-06 03:00:00",
      "exit_price": 9055.306408581224,
      "exit_reason": "TP",
      "commission": 0.08716653806445387,
      "slippage": 0.045500138675510934,
      "pnl_gross": 1.173034911134789,
      "pnl_net": 1.0858683730703351,
      "pnl_r": 0.021595259253184177,
      "holding_bars": 15
    },
    {
      "id": 43,
      "entry_time": "2020-05-05 13:00:00",
      "entry_price": 8915.422741720526,
      "side": "SELL",
      "quantity": 0.011281158670589266,
      "stop_loss": 9017.493457566716,
      "take_profit": 8731.695453197384,
      "exit_time": "2020-05-05 23:00:00",
      "exit_price": 9024.840372332335,
      "exit_reason": "SL",
      "commission": 0.15179021608631266,
      "slippage": 0.13451848813727696,
      "pnl_gross": -1.2343576522917508,
      "pnl_net": -1.3861478683780635,
      "pnl_r": -0.027564105821332483,
      "holding_bars": 10
    },
    {
      "id": 44,
      "entry_time": "2020-05-05 14:00:00",
      "entry_price": 8884.857466061483,
      "side": "BUY",
      "quantity": 0.011318407466881198,
      "stop_loss": 8781.922725434204,
      "take_profit": 9070.139999190584,
      "exit_time": "2020-05-06 08:00:00",
      "exit_price": 9065.93692178171,
      "exit_reason": "TP",
      "commission": 0.15238080392686013,
      "slippage": 0.09338301282074273,
      "pnl_gross": 2.049531063722591,
      "pnl_net": 1.897150259795731,
      "pnl_r": 0.03773079322197511,
      "holding_bars": 18
    },
    {
      "id": 45,
      "entry_time": "2020-05-05 15:00:00",
      "entry_price": 8845.21852698374,
      "side": "BUY",
      "quantity": 0.011371274579797424,
      "stop_loss": 8745.900425758378,
      "take_profit": 9023.991109189388,
      "exit_time": "2020-05-05 23:00:00",
      "exit_price": 9019.861705872509,
      "exit_reason": "TP",
      "commission": 0.15236154953843978,
      "slippage": 0.0796890996844229,
      "pnl_gross": 1.9859155406328777,
      "pnl_net": 1.8335539910944378,
      "pnl_r": 0.03645910346301241,
      "holding_bars": 8
    },
    {
      "id": 46,
      "entry_time": "2020-05-05 16:00:00",
      "entry_price": 8875.60716695731,
      "side": "BUY",
      "quantity": 0.011334407014212353,
      "stop_loss": 8778.135809823025,
      "take_profit": 9051.055609799025,
      "exit_time": "2020-05-06 03:00:00",
      "exit_price": 9046.371318857624,
      "exit_reason": "TP",
      "commission": 0.15235124899363778,
      "slippage": 0.09273197379360881,
      "pnl_gross": 1.9355104010749389,
      "pnl_net": 1.783159152081301,
      "pnl_r": 0.03545057032754752,
      "holding_bars": 11
    },
    {
      "id": 47,
      "entry_time": "2020-05-05 17:00:00",
      "entry_price": 8876.955534724138,
      "side": "BUY",
      "quantity": 0.011334694121930394,
      "stop_loss": 8779.880346102318,
      "take_profit": 9051.690874243413,
      "exit_time": "2020-05-06 03:00:00",
      "exit_price": 9049.15382260048,
      "exit_reason": "TP",
      "commission": 0.15239022477116157,
      "slippage": 0.11394299160506427,
      "pnl_gross": 1.9518149213984408,
      "pnl_net": 1.7994246966272793,
      "pnl_r": 0.03576760190751165,
      "holding_bars": 10
    },
    {
      "id": 48,
      "entry_time": "2020-05-05 18:00:00",
      "entry_price": 8892.832286360273,
      "side": "BUY",
      "quantity": 0.011316481265636275,
      "stop_loss": 8798.547838990275,
      "take_profit": 9062.544291626271,
      "exit_time": "2020-05-06 03:00:00",
      "exit_price": 9059.308555377282,
      "exit_reason": "TP",
      "commission": 0.15236629913519015,
      "slippage": 0.08100362875671448,
      "pnl_gross": 1.8839255795039984,
      "pnl_net": 1.7315592803688082,
      "pnl_r": 0.03441247028135084,
      "holding_bars": 9
    },
    {
      "id": 49,
      "entry_time": "2020-05-05 19:00:00",
      "entry_price": 8911.32803999138,
      "side": "BUY",
      "quantity": 0.011294936636620827,
      "stop_loss": 8819.17256709435,
      "take_profit": 9077.207891206033,
      "exit_time": "2020-05-06 08:00:00",
      "exit_price": 9074.56239122744,
      "exit_reason": "TP",
      "commission": 0.15236211958036605,
      "slippage": 0.10135556536702912,
      "pnl_gross": 1.84372165413121,
      "pnl_net": 1.6913595345508439,
      "pnl_r": 0.03360777041101745,
      "holding_bars": 13
    },
    {
      "id": 50,
      "entry_time": "2020-05-05 20:00:00",
      "entry_price": 8941.73692217752,
      "side": "BUY",
      "quantity": 0.011258416572903957,
      "stop_loss": 8851.504167748446,
      "take_profit": 9104.155880149854,
      "exit_time": "2020-05-06 10:00:00",
      "exit_price": 9098.23073022677,
      "exit_reason": "TP",
      "commission": 0.15232610309435984,
      "slippage": 0.10821671183738382,
      "pnl_gross": 1.7618724820985294,
      "pnl_net": 1.6095463790041695,
      "pnl_r": 0.03197674759483574,
      "holding_bars": 14
    },
    {
      "id": 51,
      "entry_time": "2020-05-05 21:00:00",
      "entry_price": 8964.777899665085,
      "side": "BUY",
      "quantity": 0.011231275972017353,
      "stop_loss": 8876.65443503982,
      "take_profit": 9123.400135990563,
      "exit_time": "2020-05-06 10:00:00",
      "exit_price": 9121.06961456096,
      "exit_reason": "TP",
      "commission": 0.15234535846507258,
      "slippage": 0.07029005446352075,
      "pnl_gross": 1.755355382135427,
      "pnl_net": 1.6030100236703544,
      "pnl_r": 0.031841799285521076,
      "holding_bars": 13
    },
    {
      "id": 52,
      "entry_time": "2020-05-05 22:00:00",
      "entry_price": 8974.268672856248,
      "side": "BUY",
      "quantity": 0.011221184521007536,
      "stop_loss": 8885.65002063099,
      "take_profit": 9133.78224686171,
      "exit_time": "2020-05-06 10:00:00",
      "exit_price": 9128.967679144087,
      "exit_reason": "TP",
      "commission": 0.1523548166499053,
      "slippage": 0.10383231989667763,
      "pnl_gross": 1.7359060947723515,
      "pnl_net": 1.5835512781224461,
      "pnl_r": 0.03145026835460773,
      "holding_bars": 12
    },
    {
      "id": 53,
      "entry_time": "2020-05-05 23:00:00",
      "entry_price": 9019.420671591432,
      "side": "SELL",
      "quantity": 0.011166766015164415,
      "stop_loss": 9108.428054891841,
      "take_profit": 8859.207381650693,
      "exit_time": "2020-05-06 10:00:00",
      "exit_price": 9116.419224853227,
      "exit_reason": "SL",
      "commission": 0.15188901045906084,
      "slippage": 0.11613993173837867,
      "pnl_gross": -1.0831601480839355,
      "pnl_net": -1.2350491585429964,
      "pnl_r": -0.024524952812654273,
      "holding_bars": 11
    },
    {
      "id": 54,
      "entry_time": "2020-05-06 00:00:00",
      "entry_price": 8953.036105997226,
      "side": "BUY",
      "quantity": 0.011248185369536853,
      "stop_loss": 8860.951352795653,
      "take_profit": 9118.788661760056,
      "exit_time": "2020-05-06 10:00:00",
      "exit_price": 9115.8995224008,
      "exit_reason": "TP",
      "commission": 0.1524320530338374,
      "slippage": 0.09870558643287847,
      "pnl_gross": 1.831917897623468,
      "pnl_net": 1.6794858445896306,
      "pnl_r": 0.033354431483250326,
      "holding_bars": 10
    },
    {
      "id": 55,
      "entry_time": "2020-05-06 01:00:00",
      "entry_price": 8983.735997500818,
      "side": "BUY",
      "quantity": 0.011211616706777552,
      "stop_loss": 8894.271414441628,
      "take_profit": 9144.772247007362,
      "exit_time": "2020-05-06 10:00:00",
      "exit_price": 9142.331956561098,
      "exit_reason": "TP",
      "commission": 0.15241689472645933,
      "slippage": 0.07036733480404064,
      "pnl_gross": 1.7781171042276407,
      "pnl_net": 1.6257002095011814,
      "pnl_r": 0.03228087026045092,
      "holding_bars": 9
    },
    {
      "id": 56,
      "entry_time": "2020-05-06 02:00:00",
      "entry_price": 8973.606306374077,
      "side": "BUY",
      "quantity": 0.011226084381415103,
      "stop_loss": 8887.730782780716,
      "take_profit": 9128.182248842126,
      "exit_time": "2020-05-06 10:00:00",
      "exit_price": 9124.69688414605,
      "exit_reason": "TP",
      "commission": 0.15237980908290985,
      "slippage": 0.06759978755066995,
      "pnl_gross": 1.6961555753049264,
      "pnl_net": 1.5437757662220166,
      "pnl_r": 0.030649182877880987,
      "holding_bars": 8
    },
    {
      "id": 57,
      "entry_time": "2020-05-06 03:00:00",
      "entry_price": 8983.312911449362,
      "side": "BUY",
      "quantity": 0.011215672920644232,
      "stop_loss": 8895.176582950107,
      "take_profit": 9141.95830274802,
      "exit_time": "2020-05-06 10:00:00",
      "exit_price": 9139.51733974746,
      "exit_reason": "TP",
      "commission": 0.1524448023703352,
      "slippage": 0.06756180554538238,
      "pnl_gross": 1.751937776547679,
      "pnl_net": 1.5994929741773438,
      "pnl_r": 0.03175049272255402,
      "holding_bars": 7
    },
    {
      "id": 58,
      "entry_time": "2020-05-06 04:00:00",
      "entry_price": 9004.466799122627,
      "side": "BUY",
      "quantity": 0.011191100654419299,
      "stop_loss": 8916.33236103538,
      "take_profit": 9163.108787679672,
      "exit_time": "2020-05-06 10:00:00",
      "exit_price": 9157.863444254459,
      "exit_reason": "TP",
      "commission": 0.15244234940432755,
      "slippage": 0.13935318061604093,
      "pnl_gross": 1.7166772957205698,
      "pnl_net": 1.5642349463162422,
      "pnl_r": 0.03104568000915245,
      "holding_bars": 6
    },
    {
      "id": 59,
      "entry_time": "2020-05-06 05:00:00",
      "entry_price": 9013.232167243079,
      "side": "BUY",
      "quantity": 0.011181952796479334,
      "stop_loss": 8927.227589670025,
      "take_profit": 9168.040406874577,
      "exit_time": "2020-05-06 10:00:00",
      "exit_price": 9162.806814489644,
      "exit_reason": "TP",
      "commission": 0.15243270744052773,
      "slippage": 0.11792218636345868,
      "pnl_gross": 1.6725366450611407,
      "pnl_net": 1.520103937620613,
      "pnl_r": 0.030165120677646356,
      "holding_bars": 5
    },
    {
      "id": 60,
      "entry_time": "2020-05-06 06:00:00",
      "entry_price": 9031.063251358097,
      "side": "BUY",
      "quantity": 0.011161558154521726,
      "stop_loss": 8948.063151569795,
      "take_profit": 9180.46343097704,
      "exit_time": "2020-05-06 10:00:00",
      "exit_price": 9174.811124129574,
      "exit_reason": "TP",
      "commission": 0.1524044441969419,
      "slippage": 0.12518310514681483,
      "pnl_gross": 1.6044502415276303,
      "pnl_net": 1.4520457973306884,
      "pnl_r": 0.028810221647002126,
      "holding_bars": 4
    },
    {
      "id": 61,
      "entry_time": "2020-05-06 07:00:00",
      "entry_price": 9023.734945422331,
      "side": "BUY",
      "quantity": 0.011172231758238149,
      "stop_loss": 8942.550966043445,
      "take_profit": 9169.866108304326,
      "exit_time": "2020-05-06 10:00:00",
      "exit_price": 9163.842643099859,
      "exit_reason": "TP",
      "commission": 0.152396873954931,
      "slippage": 0.1293566869146425,
      "pnl_gross": 1.5653156695665025,
      "pnl_net": 1.4129187956115714,
      "pnl_r": 0.028029860196700836,
      "holding_bars": 3
    },
    {
      "id": 62,
      "entry_time": "2020-05-06 08:00:00",
      "entry_price": 9044.493519555275,
      "side": "BUY",
      "quantity": 0.011148151867776972,
      "stop_loss": 8961.813340630855,
      "take_profit": 9193.31784161923,
      "exit_time": "2020-05-06 10:00:00",
      "exit_price": 9188.152207745654,
      "exit_reason": "TP",
      "commission": 0.15244522763949425,
      "slippage": 0.09965503999420762,
      "pnl_gross": 1.6015288730719588,
      "pnl_net": 1.4490836454324645,
      "pnl_r": 0.02874327978982162,
      "holding_bars": 2
    },
    {
      "id": 63,
      "entry_time": "2020-05-06 09:00:00",
      "entry_price": 9086.859854518503,
      "side": "BUY",
      "quantity": 0.011097769721785233,
      "stop_loss": 9006.02056570513,
      "take_profit": 9232.370574382574,
      "exit_time": "2020-05-06 10:00:00",
      "exit_price": 9229.47381888466,
      "exit_reason": "TP",
      "commission": 0.1524528399411067,
      "slippage": 0.07953338764802792,
      "pnl_gross": 1.582696935646498,
      "pnl_net": 1.4302440957053912,
      "pnl_r": 0.02836551155722294,
      "holding_bars": 1
    },
    {
      "id": 64,
      "entry_time": "2020-05-06 10:00:00",
      "entry_price": 9221.237732827367,
      "side": "SELL",
      "quantity": 0.010937596830573597,
      "stop_loss": 9312.479516902247,
      "take_profit": 9057.00252149258,
      "exit_time": "2020-05-06 11:00:00",
      "exit_price": 9316.098652277815,
      "exit_reason": "SL",
      "commission": 0.1520654337697523,
      "slippage": 0.10490689411194033,
      "pnl_gross": -1.0375504919265164,
      "pnl_net": -1.1896159256962686,
      "pnl_r": -0.02358987478483069,
      "holding_bars": 1
    },
    {
      "id": 65,
      "entry_time": "2020-05-06 11:00:00",
      "entry_price": 9308.814331027761,
      "side": "SELL",
      "quantity": 0.010833418828125572,
      "stop_loss": 9404.766960564617,
      "take_profit": 9136.09959786142,
      "exit_time": "2020-05-06 13:00:00",
      "exit_price": 9140.174268391747,
      "exit_reason": "TP",
      "commission": 0.149899215339619,
      "slippage": 0.08948771749381712,
      "pnl_gross": 1.8269484297372665,
      "pnl_net": 1.6770492143976474,
      "pnl_r": 0.033259514194082684,
      "holding_bars": 2
    },
    {
      "id": 66,
      "entry_time": "2020-05-06 12:00:00",
      "entry_price": 9219.778708514763,
      "side": "SELL",
      "quantity": 0.01093985638074751,
      "stop_loss": 9321.208996893316,
      "take_profit": 9037.204189433369,
      "exit_time": "2020-05-06 22:00:00",
      "exit_price": 9324.893806359745,
      "exit_reason": "SL",
      "commission": 0.15215704045554215,
      "slippage": 0.09721266819605837,
      "pnl_gross": -1.1499440738723283,
      "pnl_net": -1.3021011143278705,
      "pnl_r": -0.025819188506382706,
      "holding_bars": 10
    },
    {
      "id": 67,
      "entry_time": "2020-05-06 13:00:00",
      "entry_price": 9223.245334811723,
      "side": "SELL",
      "quantity": 0.010934332792996302,
      "stop_loss": 9328.021652934522,
      "take_profit": 9034.647962190686,
      "exit_time": "2020-05-06 22:00:00",
      "exit_price": 9333.609186731708,
      "exit_reason": "SL",
      "commission": 0.15218011719733054,
      "slippage": 0.10007318949478342,
      "pnl_gross": -1.2067550852100786,
      "pnl_net": -1.358935202407409,
      "pnl_r": -0.02694962310978784,
      "holding_bars": 9
    },
    {
      "id": 68,
      "entry_time": "2020-05-06 14:00:00",
      "entry_price": 9227.38465804887,
      "side": "SELL",
      "quantity": 0.010927955028113,
      "stop_loss": 9329.61566154414,
      "take_profit": 9043.368851757385,
      "exit_time": "2020-05-06 22:00:00",
      "exit_price": 9334.145125243575,
      "exit_reason": "SL",
      "commission": 0.1521296720435999,
      "slippage": 0.07807811483399547,
      "pnl_gross": -1.166673584284066,
      "pnl_net": -1.318803256327666,
      "pnl_r": -0.02615727402821682,
      "holding_bars": 8
    },
    {
      "id": 69,
      "entry_time": "2020-05-06 15:00:00",
      "entry_price": 9269.81347631204,
      "side": "SELL",
      "quantity": 0.010876514052341727,
      "stop_loss": 9370.30470037585,
      "take_profit": 9088.929272997182,
      "exit_time": "2020-05-06 22:00:00",
      "exit_price": 9373.699941788007,
      "exit_reason": "SL",
      "commission": 0.15208232675774003,
      "slippage": 0.07582850108105221,
      "pnl_gross": -1.1299226015974717,
      "pnl_net": -1.2820049283552117,
      "pnl_r": -0.025430738351045243,
      "holding_bars": 7
    },
    {
      "id": 70,
      "entry_time": "2020-05-06 16:00:00",
      "entry_price": 9259.351935277,
      "side": "SELL",
      "quantity": 0.010887418168471987,
      "stop_loss": 9360.039204049166,
      "take_profit": 9078.114851487102,
      "exit_time": "2020-05-06 22:00:00",
      "exit_price": 9364.659857969704,
      "exit_reason": "SL",
      "commission": 0.15207555327572306,
      "slippage": 0.12932857717784296,
      "pnl_gross": -1.1465313908085877,
      "pnl_net": -1.2986069440843107,
      "pnl_r": -0.025763343346570974,
      "holding_bars": 6
    },
    {
      "id": 71,
      "entry_time": "2020-05-06 17:00:00",
      "entry_price": 9258.646694035422,
      "side": "SELL",
      "quantity": 0.009135278831702377,
      "stop_loss": 9356.398347767281,
      "take_profit": 9082.693717318076,
      "exit_time": "2020-05-06 22:00:00",
      "exit_price": 9360.913032671846,
      "exit_reason": "SL",
      "commission": 0.12757115237025526,
      "slippage": 0.10631629163041179,
      "pnl_gross": -0.9342315185410295,
      "pnl_net": -1.0618026709112847,
      "pnl_r": -0.02106804619557028,
      "holding_bars": 5
    },
    {
      "id": 72,
      "entry_time": "2020-05-06 18:00:00",
      "entry_price": 9230.512427346628,
      "side": "SELL",
      "quantity": 0.010918877276375973,
      "stop_loss": 9326.654576410705,
      "take_profit": 9057.456559031289,
      "exit_time": "2020-05-06 22:00:00",
      "exit_price": 9333.223757533497,
      "exit_reason": "SL",
      "commission": 0.1520213678952945,
      "slippage": 0.11614140910096474,
      "pnl_gross": -1.1214924092037482,
      "pnl_net": -1.2735137770990426,
      "pnl_r": -0.02527143173113215,
      "holding_bars": 4
    },
    {
      "id": 73,
      "entry_time": "2020-05-06 19:00:00",
      "entry_price": 9235.232884771924,
      "side": "SELL",
      "quantity": 0.010911917275054063,
      "stop_loss": 9328.99367358066,
      "take_profit": 9066.463464916198,
      "exit_time": "2020-05-06 22:00:00",
      "exit_price": 9332.955112832495,
      "exit_reason": "SL",
      "commission": 0.15196089853313338,
      "slippage": 0.07047521220120168,
      "pnl_gross": -1.0663368685309182,
      "pnl_net": -1.2182977670640516,
      "pnl_r": -0.02417878800714871,
      "holding_bars": 3
    },
    {
      "id": 74,
      "entry_time": "2020-05-06 20:00:00",
      "entry_price": 9232.66763154819,
      "side": "SELL",
      "quantity": 0.010913629548681492,
      "stop_loss": 9322.976465311634,
      "take_profit": 9070.111730773988,
      "exit_time": "2020-05-06 22:00:00",
      "exit_price": 9325.44070317284,
      "exit_reason": "SL",
      "commission": 0.15190223961708277,
      "slippage": 0.06577214873602524,
      "pnl_gross": -1.012490935804741,
      "pnl_net": -1.1643931754218237,
      "pnl_r": -0.023111771620831445,
      "holding_bars": 2
    },
    {
      "id": 75,
      "entry_time": "2020-05-06 21:00:00",
      "entry_price": 9274.135187218726,
      "side": "SELL",
      "quantity": 0.007101309346572022,
      "stop_loss": 9361.70364336285,
      "take_profit": 9116.511966159303,
      "exit_time": "2020-05-06 22:00:00",
      "exit_price": 9366.314872075956,
      "exit_reason": "SL",
      "commission": 0.09927870167278374,
      "slippage": 0.053018670245929385,
      "pnl_gross": -0.6545964576407131,
      "pnl_net": -0.7538751593134968,
      "pnl_r": -0.014965223551887404,
      "holding_bars": 1
    },
    {
      "id": 76,
      "entry_time": "2020-05-06 22:00:00",
      "entry_price": 9352.999667689008,
      "side": "SELL",
      "quantity": 0.010771168092895293,
      "stop_loss": 9441.814937697456,
      "take_profit": 9193.132181673802,
      "exit_time": "2020-05-06 23:00:00",
      "exit_price": 9199.427806544523,
      "exit_reason": "TP",
      "commission": 0.14987348614216367,
      "slippage": 0.1118688906098315,
      "pnl_gross": 1.6541483307260179,
      "pnl_net": 1.504274844583854,
      "pnl_r": 0.029863689832315948,
      "holding_bars": 1
    },
    {
      "id": 77,
      "entry_time": "2020-05-06 23:00:00",
      "entry_price": 9138.447609997855,
      "side": "SELL",
      "quantity": 0.010384982664535556,
      "stop_loss": 9243.510975607162,
      "take_profit": 8949.333551901103,
      "exit_time": "2020-05-07 01:00:00",
      "exit_price": 9251.216716133233,
      "exit_reason": "SL",
      "commission": 0.14323225892512448,
      "slippage": 0.12646967442198737,
      "pnl_gross": -1.171105212311071,
      "pnl_net": -1.3143374712361955,
      "pnl_r": -0.02608905327297202,
      "holding_bars": 2
    },
    {
      "id": 78,
      "entry_time": "2020-05-07 00:00:00",
      "entry_price": 9189.004351469317,
      "side": "BUY",
      "quantity": 0.006917723798698235,
      "stop_loss": 9078.08146583198,
      "take_profit": 9388.665545616524,
      "exit_time": "2020-05-07 13:00:00",
      "exit_price": 9385.899949123239,
      "exit_reason": "TP",
      "commission": 0.09637204315406349,
      "slippage": 0.05582567107514072,
      "pnl_gross": 1.3620693617494477,
      "pnl_net": 1.2656973185953841,
      "pnl_r": 0.025126844109586228,
      "holding_bars": 13
    },
    {
      "id": 79,
      "entry_time": "2020-05-07 01:00:00",
      "entry_price": 9228.647810519804,
      "side": "BUY",
      "quantity": 0.005906825314533709,
      "stop_loss": 9121.301901280642,
      "take_profit": 9421.870447150297,
      "exit_time": "2020-05-07 13:00:00",
      "exit_price": 9417.205311892505,
      "exit_reason": "TP",
      "commission": 0.08260334792590682,
      "slippage": 0.05199746296156967,
      "pnl_gross": 1.1137762223534957,
      "pnl_net": 1.031172874427589,
      "pnl_r": 0.02046845236719026,
      "holding_bars": 12
    },
    {
      "id": 80,
      "entry_time": "2020-05-07 02:00:00",
      "entry_price": 9336.107868100065,
      "side": "BUY",
      "quantity": 0.010793319988669156,
      "stop_loss": 9223.438401649235,
      "take_profit": 9538.912907711561,
      "exit_time": "2020-05-07 13:00:00",
      "exit_price": 9535.8399755018,
      "exit_reason": "TP",
      "commission": 0.15276822891410236,
      "slippage": 0.08959319390599976,
      "pnl_gross": 2.155772547198156,
      "pnl_net": 2.0030043182840536,
      "pnl_r": 0.039754927672402525,
      "holding_bars": 11
    },
    {
      "id": 81,
      "entry_time": "2020-05-07 03:00:00",
      "entry_price": 9295.016646763956,
      "side": "BUY",
      "quantity": 0.010843189801860945,
      "stop_loss": 9183.398848503783,
      "take_profit": 9495.928683632266,
      "exit_time": "2020-05-07 13:00:00",
      "exit_price": 9488.936659082636,
      "exit_reason": "TP",
      "commission": 0.15275847819344096,
      "slippage": 0.12598345829864405,
      "pnl_gross": 2.1027114999506615,
      "pnl_net": 1.9499530217572205,
      "pnl_r": 0.03869429268895466,
      "holding_bars": 10
    },
    {
      "id": 82,
      "entry_time": "2020-05-07 04:00:00",
      "entry_price": 9282.447770275856,
      "side": "BUY",
      "quantity": 0.006948026196302585,
      "stop_loss": 9172.843721451074,
      "take_profit": 9479.735058160464,
      "exit_time": "2020-05-07 13:00:00",
      "exit_price": 9474.456559383178,
      "exit_reason": "TP",
      "commission": 0.09774259698300924,
      "slippage": 0.0775140496342386,
      "pnl_gross": 1.3340820966380096,
      "pnl_net": 1.2363394996550003,
      "pnl_r": 0.024528810788380605,
      "holding_bars": 9
    },
    {
      "id": 83,
      "entry_time": "2020-05-07 05:00:00",
      "entry_price": 9271.993301530862,
      "side": "BUY",
      "quantity": 0.010873551064892044,
      "stop_loss": 9164.410471553705,
      "take_profit": 9465.642395489744,
      "exit_time": "2020-05-07 13:00:00",
      "exit_price": 9462.525534375189,
      "exit_reason": "TP",
      "commission": 0.1527830604288047,
      "slippage": 0.06643916553971321,
      "pnl_gross": 2.0717619633406925,
      "pnl_net": 1.9189789029118878,
      "pnl_r": 0.03806761674175487,
      "holding_bars": 8
    },
    {
      "id": 84,
      "entry_time": "2020-05-07 06:00:00",
      "entry_price": 9257.019616097075,
      "side": "BUY",
      "quantity": 0.008522155929671676,
      "stop_loss": 9152.695163407854,
      "take_profit": 9444.803630937673,
      "exit_time": "2020-05-07 13:00:00",
      "exit_price": 9440.419868478797,
      "exit_reason": "TP",
      "commission": 0.1195068710798667,
      "slippage": 0.0815858248275948,
      "pnl_gross": 1.5629655483381713,
      "pnl_net": 1.4434586772583045,
      "pnl_r": 0.02862906659474724,
      "holding_bars": 7
    },
    {
      "id": 85,
      "entry_time": "2020-05-07 07:00:00",
      "entry_price": 9312.966364132099,
      "side": "BUY",
      "quantity": 0.008691117147612787,
      "stop_loss": 9210.424908471265,
      "take_profit": 9497.5409843216,
      "exit_time": "2020-05-07 13:00:00",
      "exit_price": 9493.497282096914,
      "exit_reason": "TP",
      "commission": 0.1225868840112731,
      "slippage": 0.06162059729116563,
      "pnl_gross": 1.5690153567982867,
      "pnl_net": 1.4464284727870136,
      "pnl_r": 0.028683862544293427,
      "holding_bars": 6
    },
    {
      "id": 86,
      "entry_time": "2020-05-07 08:00:00",
      "entry_price": 9347.23860868666,
      "side": "BUY",
      "quantity": 0.010791163628188884,
      "stop_loss": 9247.238197451463,
      "take_profit": 9527.239348910018,
      "exit_time": "2020-05-07 11:00:00",
      "exit_price": 9243.210934880868,
      "exit_reason": "SL",
      "commission": 0.15045943720966992,
      "slippage": 0.1340896099598551,
      "pnl_gross": -1.1225796498981688,
      "pnl_net": -1.2730390871078388,
      "pnl_r": -0.0252417887040639,
      "holding_bars": 3
    },
    {
      "id": 87,
      "entry_time": "2020-05-07 09:00:00",
      "entry_price": 9318.622598009122,
      "side": "BUY",
      "quantity": 0.007393040764401745,
      "stop_loss": 9220.507641975108,
      "take_profit": 9495.229518870348,
      "exit_time": "2020-05-07 13:00:00",
      "exit_price": 9490.752532854203,
      "exit_reason": "TP",
      "commission": 0.10429385782154772,
      "slippage": 0.07474056680994637,
      "pnl_gross": 1.2725636250835013,
      "pnl_net": 1.1682697672619535,
      "pnl_r": 0.023167349051698455,
      "holding_bars": 4
    },
    {
      "id": 88,
      "entry_time": "2020-05-07 10:00:00",
      "entry_price": 9295.416430490626,
      "side": "BUY",
      "quantity": 0.010851211923545852,
      "stop_loss": 9199.868269705345,
      "take_profit": 9467.403119904135,
      "exit_time": "2020-05-07 13:00:00",
      "exit_price": 9461.971214695697,
      "exit_reason": "TP",
      "commission": 0.1526552913525131,
      "slippage": 0.11250900796501678,
      "pnl_gross": 1.8073212602896724,
      "pnl_net": 1.6546659689371594,
      "pnl_r": 0.03280901821052309,
      "holding_bars": 3
    },
    {
      "id": 89,
      "entry_time": "2020-05-07 11:00:00",
      "entry_price": 9284.413135397985,
      "side": "BUY",
      "quantity": 0.010865854286462539,
      "stop_loss": 9191.19820261799,
      "take_profit": 9452.200014401973,
      "exit_time": "2020-05-07 13:00:00",
      "exit_price": 9445.195953067576,
      "exit_reason": "TP",
      "commission": 0.15263490239825342,
      "slippage": 0.12394893751104957,
      "pnl_gross": 1.747042668564652,
      "pnl_net": 1.5944077661663987,
      "pnl_r": 0.03160902228570467,
      "holding_bars": 2
    },
    {
      "id": 90,
      "entry_time": "2020-05-07 12:00:00",
      "entry_price": 9371.799392624038,
      "side": "BUY",
      "quantity": 0.010766238169974733,
      "stop_loss": 9277.175558641033,
      "take_profit": 9542.122293793447,
      "exit_time": "2020-05-07 13:00:00",
      "exit_price": 9536.616682173524,
      "exit_reason": "TP",
      "commission": 0.152679383158687,
      "slippage": 0.08984430321994094,
      "pnl_gross": 1.7744621938194571,
      "pnl_net": 1.6217828106607701,
      "pnl_r": 0.03214665000446859,
      "holding_bars": 1
    },
    {
      "id": 91,
      "entry_time": "2020-05-07 13:00:00",
      "entry_price": 9482.279907118298,
      "side": "SELL",
      "quantity": 0.009317283249027513,
      "stop_loss": 9590.579615446006,
      "take_profit": 9287.340432128425,
      "exit_time": "2020-05-07 16:00:00",
      "exit_price": 9594.357449836107,
      "exit_reason": "SL",
      "commission": 0.1333068252702928,
      "slippage": 0.0747984722939723,
      "pnl_gross": -1.0442582113568044,
      "pnl_net": -1.1775650366270973,
      "pnl_r": -0.02333770422191804,
      "holding_bars": 3
    },
    {
      "id": 92,
      "entry_time": "2020-05-07 14:00:00",
      "entry_price": 9494.068452118863,
      "side": "SELL",
      "quantity": 0.009762666075699531,
      "stop_loss": 9598.585888071244,
      "take_profit": 9305.937067404579,
      "exit_time": "2020-05-07 16:00:00",
      "exit_price": 9606.111109769792,
      "exit_reason": "SL",
      "commission": 0.13985150628646492,
      "slippage": 0.09710698993837141,
      "pnl_gross": -1.0938350528799408,
      "pnl_net": -1.2336865591664057,
      "pnl_r": -0.02445280824762199,
      "holding_bars": 2
    },
    {
      "id": 93,
      "entry_time": "2020-05-07 15:00:00",
      "entry_price": 9518.151133901634,
      "side": "BUY",
      "quantity": 0.010599866322253576,
      "stop_loss": 9405.569674615424,
      "take_profit": 9720.797760616812,
      "exit_time": "2020-05-07 17:00:00",
      "exit_price": 9716.71940776475,
      "exit_reason": "TP",
      "commission": 0.15291529235063767,
      "slippage": 0.07122566134333702,
      "pnl_gross": 2.1047971587896566,
      "pnl_net": 1.951881866439019,
      "pnl_r": 0.038692834010796484,
      "holding_bars": 2
    },
    {
      "id": 94,
      "entry_time": "2020-05-07 16:00:00",
      "entry_price": 9633.502912476399,
      "side": "BUY",
      "quantity": 0.010474969425953887,
      "stop_loss": 9519.576787701966,
      "take_profit": 9838.569937070377,
      "exit_time": "2020-05-07 17:00:00",
      "exit_price": 9834.168938962544,
      "exit_reason": "TP",
      "commission": 0.1529424505787445,
      "slippage": 0.07200400320653935,
      "pnl_gross": 2.1019704922700293,
      "pnl_net": 1.9490280416912849,
      "pnl_r": 0.0386287883624538,
      "holding_bars": 1
    },
    {
      "id": 95,
      "entry_time": "2020-05-07 17:00:00",
      "entry_price": 9839.909692059355,
      "side": "BUY",
      "quantity": 0.010257222059150998,
      "stop_loss": 9715.66269801218,
      "take_profit": 10063.554281344268,
      "exit_time": "2020-05-07 23:00:00",
      "exit_price": 10060.941423253871,
      "exit_reason": "TP",
      "commission": 0.15309558679190294,
      "slippage": 0.10711155574982426,
      "pnl_gross": 2.2671715489807274,
      "pnl_net": 2.1140759621888243,
      "pnl_r": 0.04189186675653247,
      "holding_bars": 6
    },
    {
      "id": 96,
      "entry_time": "2020-05-07 18:00:00",
      "entry_price": 9799.180924470445,
      "side": "BUY",
      "quantity": 0.010302012003980045,
      "stop_loss": 9674.897990272158,
      "take_profit": 10022.890206027361,
      "exit_time": "2020-05-07 23:00:00",
      "exit_price": 10016.915131372205,
      "exit_reason": "TP",
      "commission": 0.15310924457948447,
      "slippage": 0.12038930327046742,
      "pnl_gross": 2.2431004131790013,
      "pnl_net": 2.089991168599517,
      "pnl_r": 0.04140593717445642,
      "holding_bars": 5
    },
    {
      "id": 97,
      "entry_time": "2020-05-07 19:00:00",
      "entry_price": 9861.07158182862,
      "side": "SELL",
      "quantity": 0.010239473325679751,
      "stop_loss": 9992.552809517234,
      "take_profit": 9624.405371989118,
      "exit_time": "2020-05-07 23:00:00",
      "exit_price": 9995.267151234259,
      "exit_reason": "SL",
      "commission": 0.15248883810214425,
      "slippage": 0.057062126227741164,
      "pnl_gross": -1.374091953353434,
      "pnl_net": -1.5265807914555782,
      "pnl_r": -0.030237651601711293,
      "holding_bars": 4
    },
    {
      "id": 98,
      "entry_time": "2020-05-07 20:00:00",
      "entry_price": 9801.287290424767,
      "side": "BUY",
      "quantity": 0.010300372861783851,
      "stop_loss": 9666.767480134356,
      "take_profit": 10043.422948947507,
      "exit_time": "2020-05-07 23:00:00",
      "exit_price": 10040.01490688197,
      "exit_reason": "TP",
      "commission": 0.15327960802169296,
      "slippage": 0.07576266717253485,
      "pnl_gross": 2.458983461914119,
      "pnl_net": 2.305703853892426,
      "pnl_r": 0.04567698776219058,
      "holding_bars": 3
    },
    {
      "id": 99,
      "entry_time": "2020-05-07 21:00:00",
      "entry_price": 9864.796532591798,
      "side": "SELL",
      "quantity": 0.010236396698274983,
      "stop_loss": 9999.700737666879,
      "take_profit": 9621.968963456651,
      "exit_time": "2020-05-07 23:00:00",
      "exit_price": 10004.252750794007,
      "exit_reason": "SL",
      "commission": 0.15254060286173504,
      "slippage": 0.11941248643563954,
      "pnl_gross": -1.427529171559009,
      "pnl_net": -1.5800697744207441,
      "pnl_r": -0.03129471645051633,
      "holding_bars": 2
    },
    {
      "id": 100,
      "entry_time": "2020-05-07 22:00:00",
      "entry_price": 9889.137872103827,
      "side": "SELL",
      "quantity": 0.010209602825180726,
      "stop_loss": 10022.241361311675,
      "take_profit": 9649.551591529702,
      "exit_time": "2020-05-07 23:00:00",
      "exit_price": 10025.768809616755,
      "exit_reason": "SL",
      "commission": 0.15249246564067873,
      "slippage": 0.07340271749616431,
      "pnl_gross": -1.394947605639077,
      "pnl_net": -1.5474400712797558,
      "pnl_r": -0.0306532519789763,
      "holding_bars": 1
    }
  ]
}